compare_mp3/__init__.py
compare_mp3/__main__.py
compare_mp3/binary_dependencies/lame
compare_mp3/binary_dependencies/lame.exe
compare_mp3-0.1.1.dist-info/LICENSE
compare_mp3-0.1.1.dist-info/METADATA
compare_mp3-0.1.1.dist-info/WHEEL
compare_mp3-0.1.1.dist-info/entry_points.txt
compare_mp3-0.1.1.dist-info/top_level.txt
compare_mp3-0.1.1.dist-info/RECORD
