Metadata-Version: 2.1
Name: compare-mp3
Version: 0.1.1
Summary: Compare mp3 files using Python.
Home-page: https://github.com/mvasilkov/python-compare-mp3
Author: Mark Vasilkov
Author-email: mvasilkov@gmail.com
License: MIT
Keywords: compare lame mp3
Platform: UNKNOWN
Classifier: Intended Audience :: Developers
Classifier: Intended Audience :: End Users/Desktop
Classifier: License :: OSI Approved :: MIT License
Classifier: Programming Language :: Python :: 3
Classifier: Programming Language :: Python :: 3 :: Only
Classifier: Topic :: Multimedia :: Sound/Audio
Requires-Dist: mutagen (>=1.41.1)
